select2/__init__.py
select2/fields.py
select2/forms.py
select2/urls.py
select2/utils.py
select2/views.py
select2/widgets.py
select2/models/__init__.py
select2/models/base.py
select2/models/descriptors.py
select2/static/select2/css/select2-spinner.gif
select2/static/select2/css/select2.css
select2/static/select2/css/select2.png
select2/static/select2/css/select2x2.png
select2/static/select2/js/jquery-1.7.2.js
select2/static/select2/js/select2.jquery_ready.js
select2/static/select2/js/select2.jquery_ui_sortable.js
select2/static/select2/js/select2.js
select2/static/select2/js/select2.min.js
select2/static/select2/select2/LICENSE
select2/static/select2/select2/README.md
select2/static/select2/select2/component.json
select2/static/select2/select2/release.sh
select2/static/select2/select2/select2-spinner.gif
select2/static/select2/select2/select2.css
select2/static/select2/select2/select2.js
select2/static/select2/select2/select2.png
select2/static/select2/select2/select2x2.png
tests/__init__.py
tests/admin.py
tests/manage.py
tests/models.py
tests/settings.py
tests/test_admin.py
tests/urls.py
django_select2_forms-3.0.0.dist-info/LICENSE
django_select2_forms-3.0.0.dist-info/METADATA
django_select2_forms-3.0.0.dist-info/WHEEL
django_select2_forms-3.0.0.dist-info/top_level.txt
django_select2_forms-3.0.0.dist-info/RECORD
